cql_builder/__init__.py
cql_builder/assignment.py
cql_builder/base.py
cql_builder/builder.py
cql_builder/condition.py
cql_builder/selection.py
cql_builder/statement.py
cql_builder-0.2.1.dist-info/DESCRIPTION.rst
cql_builder-0.2.1.dist-info/entry_points.txt
cql_builder-0.2.1.dist-info/METADATA
cql_builder-0.2.1.dist-info/metadata.json
cql_builder-0.2.1.dist-info/RECORD
cql_builder-0.2.1.dist-info/top_level.txt
cql_builder-0.2.1.dist-info/WHEEL
