Metadata-Version: 2.0
Name: cql-builder
Version: 0.2.1
Summary: CQL generation tool
Home-page: UNKNOWN
Author: Jonathan Jengo
Author-email: jonathan.jengo@gmail.com
License: MIT
Platform: UNKNOWN
Classifier: Intended Audience :: Developers
Classifier: License :: OSI Approved :: MIT License
